[
{
"n": 1,
"text": "元素記号Fの同族元素はどれか。",
"choices": [
"C",
"O",
"P",
"Cl",
"Ar"
],
"beppu": null,
"nchoices": 5,
"flag_gap": false
},
{
"n": 2,
"text": "核反応について正しいのはどれか。",
"choices": [
"Q値が正の場合は吸熱反応である。",
"荷電粒子の加速に原子炉が使われる。",
"中性子の加速にサイクロトロンが使われる。",
"入射粒子が中性子のときクーロン障壁の影響を受ける。",
"反応を起こすために必要な最小エネルギーをしきい値と呼ぶ。"
],
"beppu": null,
"nchoices": 5,
"flag_gap": false
},
{
"n": 3,
"text": "放射性核種の分離法について正しいのはどれか。",
"choices": [
"電気泳動法では加熱を行う。",
"ペーパークロマトグラフィではRf値を比較する。",
"薄層クロマトグラフィでは移動相でキャリアガスを用いる。",
"共沈法では不要な放射性核種を沈殿させるために捕集剤を用いる。",
"イオン交換クロマトグラフィでは分離のスピードを上げるためにポンプを用いる。"
],
"beppu": null,
"nchoices": 5,
"flag_gap": false
},
{
"n": 4,
"text": "標識化合物の分解について正しいのはどれか。",
"choices": [
"分解速度はγ線で最も大きい。",
"細菌やカビによる分解を考慮する必要はない。",
"放射性壊変による分解を防止する方法はない。",
"放射線分解の起こりやすさは比放射能に関係しない。",
"ラジカルによる分解を防止するには有酸素状態が望ましい。"
],
"beppu": null,
"nchoices": 5,
"flag_gap": false
},
{
"n": 5,
"text": "X線照射野と光照射野のずれを図に示す。ずれがJIS規格の許容値を超えないのはどれか。ただし、X線は実線、光は破線、焦点から光照射野までの距離は110 cm、図中の単位はcmとする。",
"choices": [
"A",
"B",
"C",
"D",
"E"
],
"beppu": null,
"nchoices": 5,
"flag_gap": false
},
{
"n": 6,
"text": "厚生労働省通知で保守点検計画を策定すべき装置に規定されていないのはどれか。",
"choices": [
"診療用粒子線照射装置",
"血管造影X線診断装置",
"X線CT装置（医用X線CT装置）",
"磁気共鳴画像診断装置（MRI装置）",
"診療用放射線照射装置（ガンマナイフ等）"
],
"beppu": null,
"nchoices": 5,
"flag_gap": false
},
{
"n": 7,
"text": "超音波ドプラ法で正しいのはどれか。",
"choices": [
"リニア型プローブでは実施できない。",
"パワードプラ法では血流速度を知ることはできない。",
"パワードプラ法では造影剤の静注投与が必要である。",
"カラードプラ法では折り返しアーチファクトを生じない。",
"カラードプラ法では腫瘍内部の血流を表示することはできない。"
],
"beppu": null,
"nchoices": 5,
"flag_gap": false
},
{
"n": 8,
"text": "管電圧100 kV、管電流800 mA、撮影時間0.1 s、管電圧リプル百分率12％のインバータ式X線装置の公称最大電力［kW］はどれか。",
"choices": [
"59.2",
"76.0",
"80.0",
"96.0",
"125.0"
],
"beppu": null,
"nchoices": 5,
"flag_gap": false
},
{
"n": 9,
"text": "DXA方式骨密度測定装置で正しいのはどれか。",
"choices": [
"横断像を用いて測定する。",
"骨密度の単位はcm2・g−1である。",
"検出器にはBaFX：Eu2＋が用いられる。",
"アルミニウム製の基準物質を同時に測定する必要がある。",
"被検者に二つの異なるエネルギーのX線を照射して測定を行う。"
],
"beppu": null,
"nchoices": 5,
"flag_gap": false
},
{
"n": 10,
"text": "「医薬品、医療機器等の品質、有効性及び安全性の確保等に関する法律」に規定される医療機器で正しいのはどれか。",
"choices": [
"再生医療等製品は医療機器に含まれる。",
"添付文書の記載事項は規定されていない。",
"「一般医療機器」「管理医療機器」「高度管理医療機器」に分類されている。",
"「特定保守管理医療機器」は特定の条件下で保守管理が免除されるものをいう。",
"疾病の診断・治療を目的としたプログラム（ソフトウェア）は医療機器に該当しない。"
],
"beppu": null,
"nchoices": 5,
"flag_gap": false
},
{
"n": 11,
"text": "永久磁石のMRI装置の特徴について、超電導磁石のMRI装置と比較した場合に正しいのはどれか。",
"choices": [
"磁場強度が高い。",
"クエンチが発生しない。",
"磁場の安定性が優れる。",
"電波シールドが不要である。",
"傾斜磁場コイルが不要である。"
],
"beppu": null,
"nchoices": 5,
"flag_gap": false
},
{
"n": 12,
"text": "超音波検査の特徴で正しいのはどれか。",
"choices": [
"部分体積効果がない。",
"再現性は術者に依存しない。",
"任意の断層面を選択できない。",
"Mモードは心臓の検査に用いる。",
"深部の観察には高い周波数のプローブを用いる。"
],
"beppu": null,
"nchoices": 5,
"flag_gap": false
},
{
"n": 13,
"text": "DSAで正しいのはどれか。",
"choices": [
"静脈は描出できない。",
"体動の影響を受けない。",
"撮影中に画像を確認することはできない。",
"リカーシブフィルタはノイズを低減する。",
"血管の輪郭を強調するために低周波数強調フィルタを使用する。"
],
"beppu": null,
"nchoices": 5,
"flag_gap": false
},
{
"n": 14,
"text": "X線CTで誤っているのはどれか。",
"choices": [
"造影効果を高めるには管電圧を低くする。",
"管電圧が高くなるほど画像ノイズは低下する。",
"管電圧が高くなるほど金属アーチファクトは抑制される。",
"dual energy撮影により仮想的な非造影画像を作成できる。",
"管電流が大きくなるほど低コントラスト分解能は低下する。"
],
"beppu": null,
"nchoices": 5,
"flag_gap": false
},
{
"n": 15,
"text": "MRIで数値を大きくするとSN比が低下するのはどれか。",
"choices": [
"加算回数",
"静磁場強度",
"受信バンド幅",
"ボクセルサイズ",
"RFコイルの感度"
],
"beppu": null,
"nchoices": 5,
"flag_gap": false
},
{
"n": 16,
"text": "MRCP像（別冊No. 1）を別に示す。正しいのはどれか。",
"choices": [
"T1強調像である。",
"胆囊管は描出されていない。",
"ガドリニウム造影剤を用いる。",
"総胆管結石は高信号に描出される。",
"消化管内の液体信号を消すために陰性造影剤を用いる。別⟨GAP⟩冊No. 1"
],
"beppu": "1",
"nchoices": 5,
"flag_gap": true
},
{
"n": 17,
"text": "頸部MRA像（別冊No. 2）を別に示す。矢印で示すのはどれか。",
"choices": [
"外頸動脈",
"総頸動脈",
"椎骨動脈",
"内頸動脈",
"脳底動脈別⟨GAP⟩冊No. 2"
],
"beppu": "2",
"nchoices": 5,
"flag_gap": true
},
{
"n": 18,
"text": "乳房の超音波検査について正しいのはどれか。",
"choices": [
"検査前は絶食にする。",
"3.5〜5 MHzの周波数を用いる。",
"コンベックス型プローブを用いる。",
"プローブは皮膚面に対して直角に当てる。",
"マンモグラフィと比べて微小石灰化の描出に優れている。"
],
"beppu": null,
"nchoices": 5,
"flag_gap": false
},
{
"n": 19,
"text": "胆囊の超音波像（別冊No. 3）を別に示す。考えられる疾患はどれか。",
"choices": [
"胆泥",
"胆囊結石",
"壁内結石",
"胆囊腺筋腫症",
"コレステロールポリープ別⟨GAP⟩冊No. 3"
],
"beppu": "3",
"nchoices": 5,
"flag_gap": true
},
{
"n": 20,
"text": "無散瞳眼底写真について正しいのはどれか。",
"choices": [
"網膜動脈は静脈より太い。",
"網膜動脈は高血圧で太くなる。",
"中心窩は黄斑部で観察される。",
"網膜動脈と静脈は黄斑部に集まる。",
"黄斑部は視神経乳頭より鼻側に位置する。"
],
"beppu": null,
"nchoices": 5,
"flag_gap": false
},
{
"n": 21,
"text": "MRIの磁化率アーチファクトを抑制する方法で正しいのはどれか。",
"choices": [
"TEを長くする。",
"スライス厚を厚くする。",
"受信バンド幅を狭くする。",
"ピクセルサイズを大きくする。",
"GRE法ではなくSE法を用いる。"
],
"beppu": null,
"nchoices": 5,
"flag_gap": false
},
{
"n": 22,
"text": "健常成人の右肋弓下走査の超音波像（別冊No. 4）を別に示す。矢印で示すのはどれか。",
"choices": [
"門脈",
"総胆管",
"右尿管",
"右腎静脈",
"腹部大動脈別⟨GAP⟩冊No. 4"
],
"beppu": "4",
"nchoices": 5,
"flag_gap": true
},
{
"n": 23,
"text": "超音波検査で正しいのはどれか。",
"choices": [
"胆囊の検査の基本体位は右側臥位である。",
"心臓の検査にはセクタ型プローブを使用する。",
"Bモード法では連続波の超音波ビームを用いる。",
"膵臓の検査は炭酸ガスで胃を膨らませてから実施する。",
"STCの調整により距離分解能を改善することが可能である。"
],
"beppu": null,
"nchoices": 5,
"flag_gap": false
},
{
"n": 24,
"text": "MRIのIR法で正しいのはどれか。",
"choices": [
"IRパルスとして90度パルスを使用する。",
"FLAIR法は自由水の信号を抑制する目的で使用する。",
"STIR法は脂肪信号を特異的に抑制することが可能である。",
"信号を抑制したい組織の縦磁化がゼロになる時間にTRを設定する。",
"組織間の共鳴周波数の差を利用して特定組織の信号を抑制する手法である。"
],
"beppu": null,
"nchoices": 5,
"flag_gap": false
},
{
"n": 25,
"text": "ポジトロン放射性薬剤で正しいのはどれか。",
"choices": [
"13N−NH3は血液量を反映する。",
"18F−FDGは酸素代謝を反映する。",
"15O−O2ガスは糖代謝を反映する。",
"15O−CO2ガスは血流量を反映する。",
"15O−COガスは酸素消費量を反映する。"
],
"beppu": null,
"nchoices": 5,
"flag_gap": false
},
{
"n": 26,
"text": "核医学の試料計測装置で正しいのはどれか。2つ選べ。",
"choices": [
"ウェル型シンチレーションカウンタはβ線を測定する。",
"ウェル型シンチレーションカウンタの表示単位はSvである。",
"ウェル型シンチレーションカウンタは試料の液量依存性がある。",
"ウェル型電離箱放射能測定装置の測定上限値は1 GBq程度である。",
"ウェル型電離箱放射能測定装置は測定する試料の放射能が高いほど短時間で測定できる。"
],
"beppu": null,
"nchoices": 5,
"flag_gap": false
},
{
"n": 27,
"text": "放射性医薬品投与後に苦味感や金属臭がみられやすいのはどれか。",
"choices": [
"99mTc−MDP",
"99mTc−MIBI",
"99mTc−PYP",
"131I−アドステロール",
"201TlCl"
],
"beppu": null,
"nchoices": 5,
"flag_gap": false
},
{
"n": 28,
"text": "心筋血流シンチグラフィの薬剤負荷に用いるのはどれか。",
"choices": [
"アデノシン",
"フロセミド",
"サイロキシン",
"アセタゾラミド",
"デキサメサゾン"
],
"beppu": null,
"nchoices": 5,
"flag_gap": false
},
{
"n": 29,
"text": "骨シンチグラフィで正しいのはどれか。",
"choices": [
"気管支喘息患者は禁忌である。",
"放射性医薬品は大腸から排泄される。",
"小児では骨幹端部より骨幹部の集積が強い。",
"放射性医薬品投与前6時間の絶食が必要である。",
"成人の放射性医薬品の投与量は740 MBqである。"
],
"beppu": null,
"nchoices": 5,
"flag_gap": false
},
{
"n": 30,
"text": "生理的に腎臓に集積するのはどれか。",
"choices": [
"18F−FDG",
"99mTc−MAA",
"99mTc−PMT",
"123I−MIBG",
"131I−アドステロール"
],
"beppu": null,
"nchoices": 5,
"flag_gap": false
},
{
"n": 31,
"text": "疾患と放射性医薬品の組合せで正しいのはどれか。123",
"choices": [
"橋本病⟨GAP⟩ I−BMIPP 131",
"神経芽腫⟨GAP⟩ I−アドステロール",
"副甲状腺癌⟨GAP⟩ Na131I 99m",
"副甲状腺腺腫⟨GAP⟩ Tc−MIBI 99m",
"再生不良性貧血⟨GAP⟩ Tc−HSA−D"
],
"beppu": null,
"nchoices": 5,
"flag_gap": true
},
{
"n": 32,
"text": "PET装置の性能評価において、空間分解能に影響する因子として誤っているのはどれか。",
"choices": [
"角度揺動",
"収集時間",
"陽電子の飛程",
"画像再構成条件",
"検出器結晶サイズ"
],
"beppu": null,
"nchoices": 5,
"flag_gap": false
},
{
"n": 33,
"text": "2核種同時収集について誤っているのはどれか。",
"choices": [
"散乱線の低減にTEW法が有用である。",
"99mTcと201Tlの同時収集が可能である。",
"異なる放射性医薬品を用いた位置ずれのないSPECT画像が得られる。",
"半導体式のSPECT装置はシンチレーション式に比べて光電ピークの分離精度が高い。",
"異なる核種のエネルギースペクトルが相互干渉する現象をクロスキャリブレーションという。"
],
"beppu": null,
"nchoices": 5,
"flag_gap": false
},
{
"n": 34,
"text": "心電図同期心筋SPECTにおける解析で正しいのはどれか。",
"choices": [
"左室肥大の影響を受けない。",
"拡張期の心機能指標は得られない。",
"R‑R間隔の分割数が多くなるとSN比が向上する。",
"分割収集した画像を加算することで非同期の画像が得られる。",
"R‑R間隔の分割数が少なくなると収縮末期容量は過小評価となる。"
],
"beppu": null,
"nchoices": 5,
"flag_gap": false
},
{
"n": 35,
"text": "Performance Status〈PS〉スコア4の状態はどれか。",
"choices": [
"歩行できる。",
"全く動けない。",
"日中の50％以上はベッド外で過ごす。",
"自分の身の回りのことはすべてできる。",
"発病前と同じ日常生活が制限なく行える。"
],
"beppu": null,
"nchoices": 5,
"flag_gap": false
},
{
"n": 36,
"text": "臨床病期Ⅰ期で放射線単独療法が行われるのはどれか。",
"choices": [
"胃癌",
"乳癌",
"胸腺腫",
"声門癌",
"膀胱癌"
],
"beppu": null,
"nchoices": 5,
"flag_gap": false
},
{
"n": 37,
"text": "臨床標的体積〈CTV〉はどれか。",
"choices": [
"腫瘍の進展や存在が肉眼的に確認できる体積",
"すべての変動や不確実性をマージンとして付加した体積",
"予期せぬ高線量域が発生することを避けるために設定する体積",
"治療計画や処方線量に強く影響する可能性がある正常組織の体積",
"画像等で検知できないが臨床的に腫瘍の進展が疑われる部分を含む体積"
],
"beppu": null,
"nchoices": 5,
"flag_gap": false
},
{
"n": 38,
"text": "放射線治療機器のQAプログラムで正しいのはどれか。",
"choices": [
"再現性良く実行できることが重要である。",
"アクセプタンステストをまとめたものである。",
"治療機器のメーカーによる定期メンテナンスが含まれる。",
"各種ガイドラインにある数値基準を採用しなければならない。",
"コミッショニング時に作成したQAプログラムは以後変更しない。"
],
"beppu": null,
"nchoices": 5,
"flag_gap": false
},
{
"n": 39,
"text": "192 Ir線源を用いたRALSについて正しいのはどれか。",
"choices": [
"照射時に術者の被ばくを伴う。",
"5年ごとの線源交換が必要である。",
"出力測定はウェル型電離箱線量計を用いる。",
"計算アルゴリズムはSuperposition法を使用する。",
"子宮頸癌治療時の線源位置の取得には超音波装置を用いる。"
],
"beppu": null,
"nchoices": 5,
"flag_gap": false
},
{
"n": 40,
"text": "次の深部線量分布を示す放射線はどれか。",
"choices": [
"光子線",
"炭素線",
"電子線",
"陽子線",
"中性子線"
],
"beppu": null,
"nchoices": 5,
"flag_gap": false
},
{
"n": 41,
"text": "婦人科癌の治療で正しいのはどれか。",
"choices": [
"子宮頸癌に腔内照射は必要ない。",
"早期子宮頸癌は放射線治療の適応である。",
"局所進行子宮頸癌に放射線治療は行わない。",
"早期卵巣癌は放射線治療が第一選択である。",
"早期子宮体癌は放射線治療が第一選択である。"
],
"beppu": null,
"nchoices": 5,
"flag_gap": false
},
{
"n": 42,
"text": "体幹部定位放射線治療と関係ないのはどれか。",
"choices": [
"直線加速器",
"ガンマナイフ",
"呼吸同期装置",
"動体追跡装置",
"サイバーナイフ"
],
"beppu": null,
"nchoices": 5,
"flag_gap": false
},
{
"n": 43,
"text": "電離箱線量計の擾乱補正係数はどれか。2つ選べ。",
"choices": [
"空洞補正係数",
"変位補正係数",
"温度気圧補正係数",
"極性効果補正係数",
"イオン再結合補正係数"
],
"beppu": null,
"nchoices": 5,
"flag_gap": false
},
{
"n": 44,
"text": "多分割照射〈過分割照射〉を通常の分割照射と比較した場合に正しいのはどれか。",
"choices": [
"1回線量が多い。",
"総線量が等しい。",
"全治療期間が短い。",
"1日の照射回数が等しい。",
"晩期有害事象が抑えられる。"
],
"beppu": null,
"nchoices": 5,
"flag_gap": false
},
{
"n": 45,
"text": "5 × 5の画素値の分布Aに対して3 × 3の空間フィルタFを作用させた。フィルタ処理後の画素値a（i ij＝3 , j＝3）で正しいのはどれか。",
"choices": [
"1",
"2",
"3",
"4",
"5"
],
"beppu": null,
"nchoices": 5,
"flag_gap": false
},
{
"n": 46,
"text": "1ピクセルが100 μmのFPDで撮影した胸部X線画像のデータ量［MB］に最も近いのはどれか。ただし、FPDの有効視野は43 cm × 43 cm、階調数は16 bitとする。",
"choices": [
"2",
"16",
"37",
"148",
"296"
],
"beppu": null,
"nchoices": 5,
"flag_gap": false
},
{
"n": 47,
"text": "PACSについて正しいのはどれか。",
"choices": [
"画像を検索・参照する機能を持つ。",
"保存した画像は永久保存する義務がある。",
"放射線部門内で発生した画像のみ保管が可能である。",
"RISとPACS間の検査オーダ情報の伝達はDICOM規格で行う。",
"他院から提供された画像データはPACSに保管する義務がある。"
],
"beppu": null,
"nchoices": 5,
"flag_gap": false
},
{
"n": 48,
"text": "画像のデジタル化について正しいのはどれか。",
"choices": [
"量子化を行ったあとに標本化を行う。",
"ナイキスト周波数は標本化周波数の2倍である。",
"標本化定理により適切な量子化ビット数を決める。",
"量子化ビット数を増やすと量子化誤差は大きくなる。",
"最高周波数が10 cycles/mmのアナログ画像を0.1 mm間隔で標本化するとエリアシング誤差を生じる。"
],
"beppu": null,
"nchoices": 5,
"flag_gap": false
},
{
"n": 49,
"text": "フーリエ変換の性質で正しいのはどれか。ただし、( )、( )は空間の関数で、( )、( )はそれぞれの関数のフーリエ変換とする。",
"choices": [
"(2 )のフーリエ変換は(2 )である。1",
"2 ( )のフーリエ変換は⟨GAP⟩ ( )である。2",
" ( )の面積と ( )の面積は等しい。",
"( )＋( )のフーリエ変換は( ) ( )である。",
"( )と( − 2 )のフーリエ変換の絶対値は等しい。"
],
"beppu": null,
"nchoices": 5,
"flag_gap": true
},
{
"n": 50,
"text": "健常成人の体重で水が占める割合［％］に最も近いのはどれか。",
"choices": [
"5",
"20",
"40",
"60",
"90"
],
"beppu": null,
"nchoices": 5,
"flag_gap": false
},
{
"n": 51,
"text": "頸部にある筋肉はどれか。",
"choices": [
"前鋸筋",
"腓腹筋",
"円回内筋",
"外側広筋",
"胸鎖乳突筋"
],
"beppu": null,
"nchoices": 5,
"flag_gap": false
},
{
"n": 52,
"text": "呼吸について正しいのはどれか。",
"choices": [
"内呼吸は肺で行われる。",
"吸気時に横隔膜は弛緩する。",
"ガス交換は拡散によって行われる。",
"ガス交換は呼吸細気管支で行われる。",
"肺静脈より肺動脈の血中酸素分圧が高い。"
],
"beppu": null,
"nchoices": 5,
"flag_gap": false
},
{
"n": 53,
"text": "子宮動脈が分岐する血管はどれか。",
"choices": [
"大腿動脈",
"外腸骨動脈",
"内腸骨動脈",
"下腸間膜動脈",
"上腸間膜動脈"
],
"beppu": null,
"nchoices": 5,
"flag_gap": false
},
{
"n": 54,
"text": "生活習慣が発症に関連するのはどれか。",
"choices": [
"骨肉腫",
"1型糖尿病",
"多発性硬化症",
"肥大型心筋症",
"慢性閉塞性肺疾患"
],
"beppu": null,
"nchoices": 5,
"flag_gap": false
},
{
"n": 55,
"text": "骨盤を構成する骨はどれか。2つ選べ。",
"choices": [
"坐骨",
"恥骨",
"腰椎",
"肩甲骨",
"大腿骨"
],
"beppu": null,
"nchoices": 5,
"flag_gap": false
},
{
"n": 56,
"text": "脳幹を構成するのはどれか。2つ選べ。",
"choices": [
"橋",
"小脳",
"脊髄",
"大脳",
"中脳"
],
"beppu": null,
"nchoices": 5,
"flag_gap": false
},
{
"n": 57,
"text": "胸部大動脈から直接分岐するのはどれか。",
"choices": [
"内胸動脈",
"右総頸動脈",
"右椎骨動脈",
"左鎖骨下動脈",
"右鎖骨下動脈"
],
"beppu": null,
"nchoices": 5,
"flag_gap": false
},
{
"n": 58,
"text": "肝臓の機能で正しいのはどれか。",
"choices": [
"脂肪の吸収",
"胆汁の貯蔵",
"蛋白質の分解",
"インスリンの分泌",
"グリコーゲンの貯蔵"
],
"beppu": null,
"nchoices": 5,
"flag_gap": false
},
{
"n": 59,
"text": "腫瘍について正しいのはどれか。",
"choices": [
"上皮性悪性腫瘍を肉腫という。",
"早期がんは遠隔転移を起こさない。",
"遺伝子異常のある腫瘍を遺伝性腫瘍という。",
"浸潤のない悪性腫瘍を非上皮性腫瘍という。",
"進行がんの定義は臓器やがんの種類によって異なる。"
],
"beppu": null,
"nchoices": 5,
"flag_gap": false
},
{
"n": 60,
"text": "疾病や障害に対する二次予防はどれか。2つ選べ。",
"choices": [
"がん検診",
"早期治療",
"予防接種",
"生活習慣の改善",
"リハビリテーション"
],
"beppu": null,
"nchoices": 5,
"flag_gap": false
},
{
"n": 61,
"text": "舌の運動に関わる神経はどれか。",
"choices": [
"顔面神経",
"三叉神経",
"舌咽神経",
"舌下神経",
"迷走神経"
],
"beppu": null,
"nchoices": 5,
"flag_gap": false
},
{
"n": 62,
"text": "病原体の中で最も小さいのはどれか。",
"choices": [
"細菌",
"ウイルス",
"プリオン",
"リケッチア",
"スピロヘータ"
],
"beppu": null,
"nchoices": 5,
"flag_gap": false
},
{
"n": 63,
"text": "感染症に対する標準予防策〈スタンダード・プリコーション〉で用いられるのはどれか。2つ選べ。",
"choices": [
"陰圧室",
"N95マスク",
"ヘパフィルタ",
"ガウン（エプロン）",
"手指消毒用アルコール"
],
"beppu": null,
"nchoices": 5,
"flag_gap": false
},
{
"n": 64,
"text": "急性期の炎症で認められるのはどれか。",
"choices": [
"器質化",
"滲出液",
"線維化",
"瘻孔形成",
"肉芽腫形成"
],
"beppu": null,
"nchoices": 5,
"flag_gap": false
},
{
"n": 65,
"text": "内部被ばくが甲状腺癌の原因となるのはどれか。",
"choices": [
"90Sr",
"131I",
"226Ra",
"232Th",
"239Pu"
],
"beppu": null,
"nchoices": 5,
"flag_gap": false
},
{
"n": 66,
"text": "器官形成期の放射線被ばくにより胎児奇形を生じるしきい値［Gy］はどれか。",
"choices": [
"0.01",
"0.1",
"1",
"10",
"100"
],
"beppu": null,
"nchoices": 5,
"flag_gap": false
},
{
"n": 67,
"text": "細胞の放射線感受性について正しいのはどれか。",
"choices": [
"未分化なほど感受性が低い。",
"分裂頻度が高いほど感受性が高い。",
"分裂速度が速いほど感受性が低い。",
"細胞周期が短いほど感受性が低い。",
"核細胞質比が小さいほど感受性が高い。"
],
"beppu": null,
"nchoices": 5,
"flag_gap": false
},
{
"n": 68,
"text": "通常分割照射における放射線障害のしきい値が最も低いのはどれか。",
"choices": [
"肝不全",
"脳梗塞",
"白内障",
"小腸穿孔",
"間質性肺炎"
],
"beppu": null,
"nchoices": 5,
"flag_gap": false
},
{
"n": 69,
"text": "X線と同程度のLETを示すのはどれか。",
"choices": [
"α ⟨GAP⟩線",
"炭素線",
"陽子線",
"中性子線",
"ネオン線"
],
"beppu": null,
"nchoices": 5,
"flag_gap": true
},
{
"n": 70,
"text": "重水素の質量欠損に等価なエネルギー［MeV］に最も近いのはどれか。ただし、中性の重水素原子、陽子、中性子、電子の質量をそれぞれ2.0141 u、1.0073 u、1.0087 u、0.0005 uとする。また、uは統一原子質量単位で、1 uと等価なエネルギーを931.5 MeVとする。",
"choices": [
"1.1",
"2.2",
"3.3",
"4.4",
"5.5"
],
"beppu": null,
"nchoices": 5,
"flag_gap": false
},
{
"n": 71,
"text": "X線管から発生したエネルギースペクトルを図に示す。正しいのはどれか。",
"choices": [
"管電圧は100 kVである。",
"付加フィルタの吸収端が観察される。",
"K特性X線とL特性X線が観察される。",
"タングステンターゲットから発生したX線である。",
"連続スペクトルより線スペクトルの発生した割合が多い。"
],
"beppu": null,
"nchoices": 5,
"flag_gap": false
},
{
"n": 72,
"text": "質量衝突阻止能が最も大きいのはどれか。",
"choices": [
"1 MeVのα線",
"2 MeVのα線",
"2 MeVの陽子線",
"5 MeVの陽子線",
"10 MeVの炭素線"
],
"beppu": null,
"nchoices": 5,
"flag_gap": false
},
{
"n": 73,
"text": "運動エネルギー⟨GAP⟩ 0の中性子が、静止している質量［u］の原子核と反跳角θで弾性散乱したとき、原子核の反跳エネルギーを表す式はどれか。1",
"choices": [
"0 ⟨GAP⟩ cos2θ（＋1）2",
"0 ⟨GAP⟩ cos2θ（＋1）2 4",
"0 ⟨GAP⟩ cos2θ（＋1）2",
"0 ⟨GAP⟩ cos2θ（− 1）2 4",
"0 ⟨GAP⟩ cos2θ（− 1）2"
],
"beppu": null,
"nchoices": 5,
"flag_gap": true
},
{
"n": 74,
"text": "核磁気共鳴現象を起こすのはどれか。",
"choices": [
"12C",
"16O",
"22Ne",
"23Na",
"40Ca"
],
"beppu": null,
"nchoices": 5,
"flag_gap": false
},
{
"n": 75,
"text": "AD変換器の回路図を示す。正しいのはどれか。ただし、Viは入力電圧、−Vrは基準電圧である。",
"choices": [
"全ビットの比較を逐次的に行う。",
"並列比較型のAD変換器である。",
"ビデオ信号の高速AD変換に適する。",
"スタートパルス信号を加えるとS2がオンになる。",
"キャリーが与えられるとカウンタはリセットされる。"
],
"beppu": null,
"nchoices": 5,
"flag_gap": false
},
{
"n": 76,
"text": "平均値が2 mAのパルス電流を図に示す。パルスの周波数［Hz］はどれか。",
"choices": [
"10",
"20",
"30",
"50",
"100"
],
"beppu": null,
"nchoices": 5,
"flag_gap": false
},
{
"n": 77,
"text": "下図に示す回路のR3に流れる電流［A］はどれか。ただし、R1は20 Ω、R2は10 Ω、R3は30 Ω、R4は15 Ωとする。",
"choices": [
"2",
"4",
"6",
"10",
"12"
],
"beppu": null,
"nchoices": 5,
"flag_gap": false
},
{
"n": 78,
"text": "放射線計測で6つのカウント値{64，59，60，62，55，60}を得た。変動係数に最も近いのはどれか。",
"choices": [
"0.01",
"0.05",
"0.10",
"0.15",
"0.20"
],
"beppu": null,
"nchoices": 5,
"flag_gap": false
},
{
"n": 79,
"text": "GM計数管によるβ線の放射能測定において、試料台による後方散乱係数に影響しないのはどれか。",
"choices": [
"測定時間",
"試料台の厚さ",
"β線のエネルギー",
"試料台の物質の組成",
"GM計数管と試料台との距離"
],
"beppu": null,
"nchoices": 5,
"flag_gap": false
},
{
"n": 80,
"text": "ある放射性試料を計数装置で2分間測定して400カウントが得られた。また、バックグラウンドのみは1分間測定して100カウントであった。この試料の正味の計数率［cpm］とその標準偏差［cpm］に最も近いのはどれか。",
"choices": [
"100 ± 5",
"100 ± 10",
"100 ± 14",
"200 ± 20",
"300 ± 30"
],
"beppu": null,
"nchoices": 5,
"flag_gap": false
},
{
"n": 81,
"text": "質量阻止能の単位はどれか。",
"choices": [
"J",
"J・m−1",
"J・m2・kg−1",
"m−1",
"m2・kg−1"
],
"beppu": null,
"nchoices": 5,
"flag_gap": false
},
{
"n": 82,
"text": "ラジオクロミックフィルムで正しいのはどれか。",
"choices": [
"温度依存はない。",
"感度不均一はない。",
"明室で使用できない。",
"照射後の濃度上昇はない。",
"線量は直接読み取れない。"
],
"beppu": null,
"nchoices": 5,
"flag_gap": false
},
{
"n": 83,
"text": "最も低い管電圧を用いる撮影部位はどれか。",
"choices": [
"咽頭",
"喉頭",
"手指",
"乳房",
"アキレス腱"
],
"beppu": null,
"nchoices": 5,
"flag_gap": false
},
{
"n": 84,
"text": "KUBの画像（別冊No. 5）を別に示す。行われた処置はどれか。",
"choices": [
"人工血管置換術",
"尿管ステント留置術",
"消化管ステント留置術",
"イレウスチューブ挿入術",
"腹部大動脈ステントグラフト留置術別⟨GAP⟩冊No. 5"
],
"beppu": "5",
"nchoices": 5,
"flag_gap": true
},
{
"n": 85,
"text": "医療安全で正しいのはどれか。",
"choices": [
"組織の対応より個人の注意が重要である。",
"インシデントレポートの提出には医師の承認が必要である。",
"医療事故はできるだけ発生部署内で解決するように心掛ける。",
"医療事故を減らすため、一つの原因のみに重点的な対策を行う。",
"事故の原因が究明できていなくても、インシデントレポートを提出する。"
],
"beppu": null,
"nchoices": 5,
"flag_gap": false
},
{
"n": 86,
"text": "胸部X線写真（別冊No. 6）を別に示す。矢印で示す部位と名称の組合せで正しいのはどれか。",
"choices": [
"ア⟨GAP⟩食道",
"イ⟨GAP⟩大動脈弓",
"ウ⟨GAP⟩左肺静脈",
"エ⟨GAP⟩大葉間裂",
"オ⟨GAP⟩心横隔膜角別⟨GAP⟩冊No. 6"
],
"beppu": "6",
"nchoices": 5,
"flag_gap": true
},
{
"n": 87,
"text": "X線撮影の体位（別冊No. 7）を別に示す。第1斜位はどれか。",
"choices": [
"ア",
"イ",
"ウ",
"エ",
"オ別⟨GAP⟩冊No. 7"
],
"beppu": "7",
"nchoices": 5,
"flag_gap": true
},
{
"n": 88,
"text": "頸部の単純CT像（別冊No. 8）を別に示す。矢印で示すのはどれか。",
"choices": [
"横突起",
"棘突起",
"筋突起",
"歯突起",
"乳様突起別⟨GAP⟩冊No. 8"
],
"beppu": "8",
"nchoices": 5,
"flag_gap": true
},
{
"n": 89,
"text": "CTDIvolの単位で正しいのはどれか。",
"choices": [
"cm",
"mGy",
"mSv",
"mGy・cm",
"mGy/cm"
],
"beppu": null,
"nchoices": 5,
"flag_gap": false
},
{
"n": 90,
"text": "焦点−被写体間距離をa、被写体−検出器間距離をbとしたとき、拡大率はどれか。",
"choices": [
"a/b",
"b/a",
"1＋a/b",
"1＋b/a",
"1/a＋1/b"
],
"beppu": null,
"nchoices": 5,
"flag_gap": false
},
{
"n": 91,
"text": "胃部X線造影検査で誤っているのはどれか。",
"choices": [
"圧迫撮影法では凹凸病変の形態が観察できる。",
"二重造影法では陰性造影剤として炭酸ガスを使用する。",
"注腸造影検査に比べて低濃度の硫酸バリウムを使用する。",
"胃粘膜面に硫酸バリウムを付着させる目的で体位変換を行う。",
"背臥位二重造影第1斜位像では十二指腸球部から前庭部が描出される。"
],
"beppu": null,
"nchoices": 5,
"flag_gap": false
},
{
"n": 92,
"text": "子宮卵管造影検査で正しいのはどれか。",
"choices": [
"経時的に撮影する。",
"40 kV程度の管電圧で撮影する。",
"骨盤計測を目的とした検査である。",
"造影剤投与後にKUB撮影を実施する。",
"油性ヨード造影剤の使用は禁忌である。"
],
"beppu": null,
"nchoices": 5,
"flag_gap": false
},
{
"n": 93,
"text": "X線画像の被写体コントラストを決定するのはどれか。2つ選べ。",
"choices": [
"被写体の厚さ",
"検出器の入出力特性",
"入射X線のスペクトル",
"被写体に入射する光子数",
"検出器に入射する散乱線"
],
"beppu": null,
"nchoices": 5,
"flag_gap": false
},
{
"n": 94,
"text": "図に標本化間隔0.1 mmのCRシステムを用いてエッジをわずかに傾斜させて計測したプリサンプルドMTFを示す。このCRシステムの4 cycles/mmのデジタルMTF値に最も近いのはどれか。",
"choices": [
"0.15",
"0.22",
"0.35",
"0.46",
"0.50"
],
"beppu": null,
"nchoices": 5,
"flag_gap": false
},
{
"n": 95,
"text": "X線写真のウィナースペクトルについて正しいのはどれか。",
"choices": [
"体積の次元を持つ。",
"X線量が少ないほど値が小さくなる。",
"高空間周波数領域は量子モトルに影響される。",
"値が大きいほど低コントラスト信号の検出能は優れる。",
"濃度変動をフーリエ変換しその絶対値を2乗して求める。"
],
"beppu": null,
"nchoices": 5,
"flag_gap": false
},
{
"n": 96,
"text": "医療法施行規則で規定されているエックス線診療室の構造設備基準で、画壁等の外側における実効線量限度として正しいのはどれか。",
"choices": [
"250 µSv/ 3月",
"1 mSv/年",
"2 mSv/年",
"1.3 mSv/ 3月",
"1 mSv/週"
],
"beppu": null,
"nchoices": 5,
"flag_gap": false
},
{
"n": 97,
"text": "診療放射線技師法で正しいのはどれか。",
"choices": [
"診療放射線技師が業務を行う場所は病院又は診療所に限定される。",
"免許を取り消された者は、30日以内に免許証を返納しなければならない。",
"規定する放射線に百万電子ボルト未満のエネルギーを有する電子線が含まれる。",
"照射録には、その照射について指示をした医師又は歯科医師の署名を受けなければならない。",
"業務上知り得た人の秘密を漏らしてはならないが、診療放射線技師でなくなった後はこの限りではない。"
],
"beppu": null,
"nchoices": 5,
"flag_gap": false
},
{
"n": 98,
"text": "国際放射線防護委員会〈ICRP〉2007年勧告における実効線量で正しいのはどれか。",
"choices": [
"特定の個人に対する線量である。",
"線量計を用いて直接測定することができる。",
"内部被ばくの管理には預託実効線量を用いる。",
"個人のリスク評価のための使用が推奨されている。",
"被ばくによる組織反応〈確定的影響〉のリスクの程度を表す線量である。"
],
"beppu": null,
"nchoices": 5,
"flag_gap": false
},
{
"n": 99,
"text": "特定放射性同位元素である核種はどれか。",
"choices": [
"PET検査用18F",
"甲状腺癌内用療法用131I",
"高線量率RALS治療用192Ir",
"前立腺癌永久挿入治療用125I",
"骨転移を有する去勢抵抗性前立腺癌内用療法用223Ra"
],
"beppu": null,
"nchoices": 5,
"flag_gap": false
},
{
"n": 100,
"text": "内部被ばくの線量評価で正しいのはどれか。",
"choices": [
"空気中放射性物質濃度測定法は最も精度が高い。",
"体外計測法では残留関数を用いて摂取量を評価する。",
"MIRD法では排泄物中の放射性物質濃度を用いて評価する。",
"実効線量係数は放射性物質濃度の種類によらず一定である。",
"バイオアッセイ法は主にγ線を放出する放射性物質を対象とする。"
],
"beppu": null,
"nchoices": 5,
"flag_gap": false
}
]